setup.py
gcpy_utils/__init__.py
gcpy_utils/simple_config.py
gcpy_utils/upyun.py
gcpy_utils.egg-info/PKG-INFO
gcpy_utils.egg-info/SOURCES.txt
gcpy_utils.egg-info/dependency_links.txt
gcpy_utils.egg-info/requires.txt
gcpy_utils.egg-info/top_level.txt
gcpy_utils/celery_utils/__init__.py
gcpy_utils/celery_utils/log_to_system.py
gcpy_utils/django/__init__.py
gcpy_utils/django/storages/__init__.py
gcpy_utils/django/storages/upyun_storage.py
gcpy_utils/spider_utils/__init__.py
gcpy_utils/spider_utils/async_crawl.py
gcpy_utils/spider_utils/async_dataflow_push.py
gcpy_utils/spider_utils/async_image_push.py
gcpy_utils/spider_utils/sync_dataflow_push.py
gcpy_utils/spider_utils/sync_image_push.py