Metadata-Version: 1.0
Name: gcpy-utils
Version: 0.2.14
Summary: <公用函数的封装>
Home-page: UNKNOWN
Author: zhoukunpeng
Author-email: zhoukunpeng504@163.com
License: UNKNOWN
Platform: UNKNOWN
